ai.py
pysheets.py
datafiles/forbes-ai-50.csv
static/__init__.py
static/api.py
static/constants.py
static/editor.py
static/history.py
static/html_maker.py
static/inventory.py
static/lsp.py
static/menu.py
static/models.py
static/preview.py
static/pysheets.css
static/pysheets.py
static/selection.py
static/state.py
static/storage.py
static/timeline.py
static/worker.py
static/worker_patch.py
static/icons/favicon.ico
static/icons/format-color-fill.png
static/icons/format-color-text.png
static/icons/logo.png
static/icons/person.png
static/icons/python-popularity.png
static/icons/screenshot-accounting.png
static/icons/screenshot-airports.png
static/icons/screenshot-basics.png
static/icons/screenshot-charts.png
static/icons/screenshot-chess.png
static/icons/screenshot-cloudslurp.png
static/icons/screenshot-duckdb.png
static/icons/screenshot-quack.png
static/icons/screenshot.png
static/icons/screenshot1.png
static/icons/screenshot2.png
static/lib/codemirror.js
static/lib/codemirror.min.css
static/lib/html2canvas.min.js
static/lib/jquery.min.js
static/lib/jqueryui.min.css
static/lib/jqueryui.min.js
static/lib/leader-line.min.js
static/lib/package-lock.json
static/lib/package.json
static/lib/python.min.js
static/lib/images/ui-icons_444444_256x240.png
static/lib/images/ui-icons_555555_256x240.png
static/lib/images/ui-icons_777620_256x240.png
static/lib/images/ui-icons_777777_256x240.png
static/lib/images/ui-icons_cc0000_256x240.png
static/lib/images/ui-icons_ffffff_256x240.png
static/views/__init__.py
static/views/cell.py
static/views/spreadsheet.py
templates/about.html
templates/index.html
pysheets_app-0.5.8.dist-info/LICENSE
pysheets_app-0.5.8.dist-info/METADATA
pysheets_app-0.5.8.dist-info/WHEEL
pysheets_app-0.5.8.dist-info/entry_points.txt
pysheets_app-0.5.8.dist-info/top_level.txt
pysheets_app-0.5.8.dist-info/RECORD
