Metadata-Version: 2.2
Name: pysheets-app
Version: 0.5.8
Summary: A Spreadsheet UI for Python
Author-email: Chris Laffra <chris@chrislaffra.com>
License: # INTRODUCTION
Project-URL: Homepage, https://pysheets.app
Keywords: spreadsheets,pyscript,local-first
Classifier: Programming Language :: Python
Classifier: Programming Language :: Python :: 3
Requires-Python: >=3.10
License-File: LICENSE
Requires-Dist: Werkzeug>=2.2.2
Requires-Dist: requests>=2.28.2
Requires-Dist: flask>=2.1.0
Requires-Dist: openai>=0.28
Requires-Dist: certifi>=2024.8.30
Requires-Dist: pyscript-ltk>=0.1.43
Provides-Extra: dev
Requires-Dist: mock; extra == "dev"
Requires-Dist: pytest; extra == "dev"
